MANIFEST.in
README.rst
setup.py
bases/__init__.py
bases/admin.py
bases/models.py
bases/tests.py
bases/urls.py
bases/views.py
bases/static/bases/base.js
bases/templates/bases/base.html
bases/templates/bases/base_with_nav.html
djangoapps_bases.egg-info/PKG-INFO
djangoapps_bases.egg-info/SOURCES.txt
djangoapps_bases.egg-info/dependency_links.txt
djangoapps_bases.egg-info/top_level.txt